stix_shifter_modules/reversinglabs/__init__.py
stix_shifter_modules/reversinglabs/entry_point.py
stix_shifter_modules/reversinglabs/configuration/config.json
stix_shifter_modules/reversinglabs/configuration/dialects.json
stix_shifter_modules/reversinglabs/configuration/lang_en.json
stix_shifter_modules/reversinglabs/stix_translation/__init__.py
stix_shifter_modules/reversinglabs/stix_translation/json_to_stix_translator.py
stix_shifter_modules/reversinglabs/stix_translation/query_constructor.py
stix_shifter_modules/reversinglabs/stix_translation/query_translator.py
stix_shifter_modules/reversinglabs/stix_translation/results_translator.py
stix_shifter_modules/reversinglabs/stix_translation/sdo_translator.py
stix_shifter_modules/reversinglabs/stix_translation/json/from_stix_map.json
stix_shifter_modules/reversinglabs/stix_translation/json/operators.json
stix_shifter_modules/reversinglabs/stix_translation/json/to_stix_map.json
stix_shifter_modules/reversinglabs/stix_transmission/__init__.py
stix_shifter_modules/reversinglabs/stix_transmission/api_client.py
stix_shifter_modules/reversinglabs/stix_transmission/delete_connector.py
stix_shifter_modules/reversinglabs/stix_transmission/error_mapper.py
stix_shifter_modules/reversinglabs/stix_transmission/ping_connector.py
stix_shifter_modules/reversinglabs/stix_transmission/results_connector.py
stix_shifter_modules_reversinglabs-8.0.2.dist-info/licenses/AUTHORS.md
stix_shifter_modules_reversinglabs-8.0.2.dist-info/licenses/LICENSE.md
stix_shifter_modules_reversinglabs-8.0.2.dist-info/licenses/NOTICE
stix_shifter_modules_reversinglabs-8.0.2.dist-info/METADATA
stix_shifter_modules_reversinglabs-8.0.2.dist-info/WHEEL
stix_shifter_modules_reversinglabs-8.0.2.dist-info/top_level.txt
stix_shifter_modules_reversinglabs-8.0.2.dist-info/RECORD
